pushl/__init__.py
pushl/__main__.py
pushl/__version__.py
pushl/caching.py
pushl/entries.py
pushl/feeds.py
pushl/utils.py
pushl/webmentions.py
pushl/websub.py
pushl-0.4.1.dist-info/METADATA
pushl-0.4.1.dist-info/WHEEL
pushl-0.4.1.dist-info/entry_points.txt
pushl-0.4.1.dist-info/licenses/LICENSE
pushl-0.4.1.dist-info/RECORD
