Metadata-Version: 2.4
Name: Pushl
Version: 0.4.1
Summary: A conduit for pushing changes in a feed to the rest of the IndieWeb
License: MIT
License-File: LICENSE
Author: fluffy
Author-email: fluffy@beesbuzz.biz
Requires-Python: >=3.10.0,<4.0.0
Classifier: License :: OSI Approved :: MIT License
Classifier: Programming Language :: Python :: 3
Classifier: Programming Language :: Python :: 3.10
Classifier: Programming Language :: Python :: 3.11
Classifier: Programming Language :: Python :: 3.12
Classifier: Programming Language :: Python :: 3.13
Classifier: Programming Language :: Python :: 3.14
Requires-Dist: aiohttp (>=3.13.3,<4.0.0)
Requires-Dist: async-lru (>=2.0.5,<3.0.0)
Requires-Dist: awesome-slugify (>=1.6.5,<2.0.0)
Requires-Dist: beautifulsoup4 (>=4.14.3,<5.0.0)
Requires-Dist: feedparser (>=6.0.12,<7.0.0)
Requires-Dist: mf2py (>=2.0.1,<3.0.0)
Project-URL: Homepage, https://plaidweb.site/
Project-URL: Repository, https://github.com/PlaidWeb/Pushl
